{
  "plugins": [
    "react",
    "import"
  ],
  "rules": {
    "react/forbid-elements": [
      "warn",
      {
        "forbid": []
      }
    ],
    "no-restricted-imports": [
      "warn",
      {
        "patterns": []
      }
    ],
    "no-restricted-syntax": [
      "warn",
      {
        "selector": "Literal[value=/#[0-9a-fA-F]{3,8}\\b/]",
        "message": "Raw hex color — use a design-system color token via var()."
      },
      {
        "selector": "Literal[value=/\\b\\d+px\\b/]",
        "message": "Raw px value — use a design-system spacing token via var()."
      },
      {
        "selector": "Literal[value=/font-family\\s*:\\s*(?!['\\\"]?(?:Inter))/i]",
        "message": "Font not provided by the design system. Available: Inter."
      }
    ]
  },
  "overrides": [
    {
      "files": [
        "**/index.js"
      ],
      "rules": {
        "no-restricted-imports": "off"
      }
    }
  ],
  "x-omelette": {
    "components": {},
    "tokens": [
      "--luml-bg",
      "--luml-bg-card",
      "--luml-bg-hover",
      "--luml-body-lh",
      "--luml-body-size",
      "--luml-body-weight",
      "--luml-border",
      "--luml-border-strong",
      "--luml-brand",
      "--luml-brand-active",
      "--luml-brand-contrast",
      "--luml-brand-hover",
      "--luml-brand-tint",
      "--luml-brand-tint-strong",
      "--luml-button-h",
      "--luml-button-size",
      "--luml-button-weight",
      "--luml-caption-size",
      "--luml-caption-weight",
      "--luml-contrast",
      "--luml-danger",
      "--luml-danger-tint-bg",
      "--luml-danger-tint-fg",
      "--luml-fg",
      "--luml-fg-faint",
      "--luml-fg-muted",
      "--luml-fg-strong",
      "--luml-font-mono",
      "--luml-font-sans",
      "--luml-gradient-brand",
      "--luml-gradient-brand-dark",
      "--luml-h1-lh",
      "--luml-h1-size",
      "--luml-h1-tracking",
      "--luml-h1-weight",
      "--luml-header-height",
      "--luml-help",
      "--luml-info",
      "--luml-info-tint-bg",
      "--luml-info-tint-fg",
      "--luml-input-padding-x",
      "--luml-input-padding-y",
      "--luml-radius-lg",
      "--luml-radius-md",
      "--luml-radius-pill",
      "--luml-radius-sm",
      "--luml-radius-xs",
      "--luml-shadow-card",
      "--luml-shadow-input",
      "--luml-shadow-message-info",
      "--luml-shadow-message-success",
      "--luml-shadow-modal",
      "--luml-shadow-popover",
      "--luml-sidebar-closed-width",
      "--luml-sidebar-width",
      "--luml-space-1",
      "--luml-space-10",
      "--luml-space-2",
      "--luml-space-3",
      "--luml-space-4",
      "--luml-space-5",
      "--luml-space-6",
      "--luml-space-8",
      "--luml-sub-title-lh",
      "--luml-success",
      "--luml-success-tint-bg",
      "--luml-success-tint-fg",
      "--luml-surface-0",
      "--luml-surface-100",
      "--luml-surface-200",
      "--luml-surface-300",
      "--luml-surface-400",
      "--luml-surface-50",
      "--luml-surface-500",
      "--luml-surface-600",
      "--luml-surface-700",
      "--luml-surface-800",
      "--luml-surface-900",
      "--luml-surface-950",
      "--luml-text-2xl",
      "--luml-text-base",
      "--luml-text-lg",
      "--luml-text-md",
      "--luml-text-sm",
      "--luml-text-xl",
      "--luml-text-xs",
      "--luml-title-lh",
      "--luml-title-size",
      "--luml-title-weight",
      "--luml-warn",
      "--luml-warn-tint-bg",
      "--luml-warn-tint-fg"
    ],
    "tokenKinds": {
      "--luml-brand": "color",
      "--luml-brand-hover": "color",
      "--luml-brand-active": "color",
      "--luml-brand-contrast": "color",
      "--luml-brand-tint": "color",
      "--luml-brand-tint-strong": "color",
      "--luml-gradient-brand": "other",
      "--luml-gradient-brand-dark": "other",
      "--luml-surface-0": "color",
      "--luml-surface-50": "color",
      "--luml-surface-100": "color",
      "--luml-surface-200": "color",
      "--luml-surface-300": "color",
      "--luml-surface-400": "color",
      "--luml-surface-500": "color",
      "--luml-surface-600": "color",
      "--luml-surface-700": "color",
      "--luml-surface-800": "color",
      "--luml-surface-900": "color",
      "--luml-surface-950": "color",
      "--luml-bg": "color",
      "--luml-bg-hover": "color",
      "--luml-bg-card": "color",
      "--luml-border": "color",
      "--luml-border-strong": "color",
      "--luml-fg": "color",
      "--luml-fg-strong": "color",
      "--luml-fg-muted": "color",
      "--luml-fg-faint": "color",
      "--luml-success": "color",
      "--luml-success-tint-bg": "color",
      "--luml-success-tint-fg": "color",
      "--luml-info": "color",
      "--luml-info-tint-bg": "color",
      "--luml-info-tint-fg": "color",
      "--luml-warn": "color",
      "--luml-warn-tint-bg": "color",
      "--luml-warn-tint-fg": "color",
      "--luml-danger": "color",
      "--luml-danger-tint-bg": "color",
      "--luml-danger-tint-fg": "color",
      "--luml-help": "color",
      "--luml-contrast": "color",
      "--luml-font-sans": "font",
      "--luml-font-mono": "font",
      "--luml-text-xs": "font",
      "--luml-text-sm": "font",
      "--luml-text-base": "font",
      "--luml-text-md": "font",
      "--luml-text-lg": "font",
      "--luml-text-xl": "font",
      "--luml-text-2xl": "font",
      "--luml-h1-size": "spacing",
      "--luml-h1-weight": "font",
      "--luml-h1-lh": "other",
      "--luml-h1-tracking": "font",
      "--luml-title-size": "spacing",
      "--luml-title-weight": "font",
      "--luml-title-lh": "other",
      "--luml-sub-title-lh": "other",
      "--luml-body-size": "spacing",
      "--luml-body-weight": "font",
      "--luml-body-lh": "other",
      "--luml-button-size": "spacing",
      "--luml-button-weight": "font",
      "--luml-caption-size": "spacing",
      "--luml-caption-weight": "font",
      "--luml-radius-xs": "radius",
      "--luml-radius-sm": "radius",
      "--luml-radius-md": "radius",
      "--luml-radius-lg": "radius",
      "--luml-radius-pill": "radius",
      "--luml-shadow-input": "shadow",
      "--luml-shadow-card": "shadow",
      "--luml-shadow-popover": "shadow",
      "--luml-shadow-modal": "shadow",
      "--luml-shadow-message-info": "shadow",
      "--luml-shadow-message-success": "shadow",
      "--luml-space-1": "spacing",
      "--luml-space-2": "spacing",
      "--luml-space-3": "spacing",
      "--luml-space-4": "spacing",
      "--luml-space-5": "spacing",
      "--luml-space-6": "spacing",
      "--luml-space-8": "spacing",
      "--luml-space-10": "spacing",
      "--luml-header-height": "spacing",
      "--luml-sidebar-width": "spacing",
      "--luml-sidebar-closed-width": "spacing",
      "--luml-button-h": "spacing",
      "--luml-input-padding-x": "spacing",
      "--luml-input-padding-y": "spacing"
    },
    "fontFamilies": [
      "Inter"
    ]
  }
}